ai_security_analyzer/__init__.py
ai_security_analyzer/agent_builder.py
ai_security_analyzer/app.py
ai_security_analyzer/base_agent.py
ai_security_analyzer/checkpointing.py
ai_security_analyzer/components.py
ai_security_analyzer/config.py
ai_security_analyzer/constants.py
ai_security_analyzer/documents.py
ai_security_analyzer/dry_run.py
ai_security_analyzer/file_agents.py
ai_security_analyzer/full_dir_scan_agents.py
ai_security_analyzer/github2_agents.py
ai_security_analyzer/github2_deep_base_agents.py
ai_security_analyzer/github2as_agents.py
ai_security_analyzer/github2at_agents.py
ai_security_analyzer/github2ms_agents.py
ai_security_analyzer/github2sd_agents.py
ai_security_analyzer/github2tm_agents.py
ai_security_analyzer/graphs.py
ai_security_analyzer/llms.py
ai_security_analyzer/loaders.py
ai_security_analyzer/model_configs.yaml
ai_security_analyzer/prompts/__init__.py
ai_security_analyzer/prompts/default/dir/attack-surface-default.yaml
ai_security_analyzer/prompts/default/dir/attack-tree-default.yaml
ai_security_analyzer/prompts/default/dir/doc-types-default.yaml
ai_security_analyzer/prompts/default/dir/mitigations-default.yaml
ai_security_analyzer/prompts/default/dir/sec-design-default.yaml
ai_security_analyzer/prompts/default/dir/threat-modeling-default.yaml
ai_security_analyzer/prompts/default/dir/vulnerabilities-default.yaml
ai_security_analyzer/prompts/default/dir/vulnerabilities-workflow-1-default.yaml
ai_security_analyzer/prompts/default/dir/vulnerabilities-workflow-2-default.yaml
ai_security_analyzer/prompts/default/file/attack-surface-default.yaml
ai_security_analyzer/prompts/default/file/attack-tree-default.yaml
ai_security_analyzer/prompts/default/file/doc-types-default.yaml
ai_security_analyzer/prompts/default/file/mitigations-default.yaml
ai_security_analyzer/prompts/default/file/sec-design-default.yaml
ai_security_analyzer/prompts/default/file/threat-modeling-default.yaml
ai_security_analyzer/prompts/default/github/attack-surface-default.yaml
ai_security_analyzer-0.0.55.dist-info/LICENSE
ai_security_analyzer-0.0.55.dist-info/METADATA
ai_security_analyzer-0.0.55.dist-info/WHEEL
ai_security_analyzer-0.0.55.dist-info/RECORD
