Metadata-Version: 2.3
Name: ai-security-analyzer
Version: 0.0.55
Summary: 
License: MIT
Author: xvnpw
Author-email: 17719543+xvnpw@users.noreply.github.com
Requires-Python: >=3.11,<4.0
Classifier: License :: OSI Approved :: MIT License
Classifier: Programming Language :: Python :: 3
Classifier: Programming Language :: Python :: 3.11
Classifier: Programming Language :: Python :: 3.12
Classifier: Programming Language :: Python :: 3.13
Requires-Dist: langchain-anthropic (>=0.3.0,<0.4.0)
Requires-Dist: langchain-community (>=0.3.8,<0.4.0)
Requires-Dist: langchain-core (>=0.3.21,<0.4.0)
Requires-Dist: langchain-google-genai (>=2.0.7,<3.0.0)
Requires-Dist: langchain-openai (>=0.2.10,<0.3.0)
Requires-Dist: langchain-text-splitters (>=0.3.2,<0.4.0)
Requires-Dist: langgraph (>=0.2.53,<0.3.0)
Requires-Dist: langgraph-checkpoint-sqlite (>=2.0.2,<3.0.0)
Requires-Dist: langgraph-sdk (>=0.1.40,<0.2.0)
Requires-Dist: langsmith (>=0.1.147,<0.2.0)
Requires-Dist: pathvalidate (>=3.2.2,<4.0.0)
Requires-Dist: pyyaml (>=6.0.2,<7.0.0)
Requires-Dist: six (>=1.16.0,<2.0.0)
Requires-Dist: types-pyyaml (>=6.0.12.20241230,<7.0.0.0)
